[
null,
{"id":1,"animationId":-1,"damage":{"critical":true,"elementId":-1,"formula":"a.weaponDamage(b)","type":1,"variance":10},"description":"","effects":[{"code":21,"dataId":0,"value1":1,"value2":0}],"hitType":1,"iconIndex":76,"message1":" attacks!","message2":"","mpCost":0,"name":"Attack","note":"Skill #1 will be used when you select\nthe Attack command.","occasion":1,"repeats":1,"requiredWtypeId1":0,"requiredWtypeId2":0,"scope":1,"speed":0,"stypeId":0,"successRate":100,"tpCost":0,"tpGain":10},
{"id":2,"animationId":0,"damage":{"critical":false,"elementId":0,"formula":"0","type":0,"variance":20},"description":"","effects":[{"code":21,"dataId":2,"value1":1,"value2":0}],"hitType":0,"iconIndex":128,"message1":" guards.","message2":"","mpCost":0,"name":"Guard","note":"Skill #2 will be used when you select\nthe Guard command.","occasion":1,"repeats":1,"requiredWtypeId1":0,"requiredWtypeId2":0,"scope":11,"speed":2000,"stypeId":0,"successRate":100,"tpCost":0,"tpGain":10},
{"id":3,"animationId":0,"damage":{"critical":false,"elementId":0,"formula":"0","type":0,"variance":20},"description":"","effects":[{"code":41,"dataId":0,"value1":0,"value2":0}],"hitType":0,"iconIndex":82,"message1":" flees.","message2":"","mpCost":0,"name":"Escape","note":"","occasion":1,"repeats":1,"requiredWtypeId1":0,"requiredWtypeId2":0,"scope":11,"speed":0,"stypeId":0,"successRate":100,"tpCost":0,"tpGain":0},
{"id":4,"animationId":0,"damage":{"critical":false,"elementId":0,"formula":"0","type":0,"variance":20},"description":"","effects":[],"hitType":0,"iconIndex":0,"message1":" waits.","message2":"","mpCost":0,"name":"Wait","note":"","occasion":1,"repeats":1,"requiredWtypeId1":0,"requiredWtypeId2":0,"scope":0,"speed":0,"stypeId":0,"successRate":100,"tpCost":0,"tpGain":0},
{"id":5,"animationId":0,"damage":{"critical":false,"elementId":0,"formula":"0","type":0,"variance":20},"description":"","effects":[],"hitType":0,"iconIndex":0,"message1":"","message2":"","mpCost":0,"name":"","note":"","occasion":0,"repeats":1,"requiredWtypeId1":0,"requiredWtypeId2":0,"scope":1,"speed":0,"stypeId":1,"successRate":100,"tpCost":0,"tpGain":0},
{"id":6,"animationId":0,"damage":{"critical":false,"elementId":0,"formula":"0","type":0,"variance":20},"description":"","effects":[],"hitType":0,"iconIndex":0,"message1":"","message2":"","mpCost":0,"name":"--WHITE MAGICK--","note":"","occasion":0,"repeats":1,"requiredWtypeId1":0,"requiredWtypeId2":0,"scope":1,"speed":0,"stypeId":1,"successRate":100,"tpCost":0,"tpGain":0},
{"id":7,"animationId":41,"damage":{"critical":false,"elementId":0,"formula":"(46 * Math.Random(0,0.125)+1) * (2 + a.mat * (a.level + a.mat)/256)","type":3,"variance":0},"description":"Restores some HP to one target. May remove negative status effects.","effects":[],"hitType":0,"iconIndex":72,"message1":" casts %1!","message2":"","mpCost":8,"name":"Cure","note":"","occasion":0,"repeats":1,"requiredWtypeId1":0,"requiredWtypeId2":0,"scope":7,"speed":-23,"stypeId":5,"successRate":100,"tpCost":0,"tpGain":0},
{"id":8,"animationId":46,"damage":{"critical":false,"elementId":0,"formula":"0","type":0,"variance":20},"description":"Removes Blind from one target.","effects":[],"hitType":0,"iconIndex":72,"message1":" casts %1!","message2":"","mpCost":6,"name":"Blindna","note":"","occasion":0,"repeats":1,"requiredWtypeId1":0,"requiredWtypeId2":0,"scope":7,"speed":-23,"stypeId":5,"successRate":100,"tpCost":0,"tpGain":0},
{"id":9,"animationId":46,"damage":{"critical":false,"elementId":0,"formula":"0","type":0,"variance":20},"description":"Removes Silence from one target.","effects":[],"hitType":0,"iconIndex":72,"message1":" casts %1!","message2":"","mpCost":8,"name":"Vox","note":"","occasion":0,"repeats":1,"requiredWtypeId1":0,"requiredWtypeId2":0,"scope":7,"speed":-23,"stypeId":5,"successRate":100,"tpCost":0,"tpGain":0},
{"id":10,"animationId":46,"damage":{"critical":false,"elementId":0,"formula":"0","type":0,"variance":20},"description":"Removes Poison from one target.","effects":[],"hitType":0,"iconIndex":72,"message1":" casts %1!","message2":"","mpCost":8,"name":"Poisona","note":"","occasion":0,"repeats":1,"requiredWtypeId1":0,"requiredWtypeId2":0,"scope":7,"speed":-23,"stypeId":5,"successRate":100,"tpCost":0,"tpGain":0},
{"id":11,"animationId":53,"damage":{"critical":false,"elementId":0,"formula":"0","type":0,"variance":20},"description":"One target gains Protect, boosting Defense.","effects":[{"code":31,"dataId":3,"value1":5,"value2":0}],"hitType":0,"iconIndex":73,"message1":" casts %1!","message2":"","mpCost":8,"name":"Protect","note":"","occasion":1,"repeats":1,"requiredWtypeId1":0,"requiredWtypeId2":0,"scope":7,"speed":0,"stypeId":5,"successRate":100,"tpCost":0,"tpGain":0},
{"id":12,"animationId":53,"damage":{"critical":false,"elementId":0,"formula":"0","type":0,"variance":20},"description":"One target gains Shell, boosting Magick Defense.","effects":[{"code":31,"dataId":5,"value1":5,"value2":0}],"hitType":0,"iconIndex":73,"message1":" casts %1!","message2":"","mpCost":8,"name":"Shell","note":"","occasion":1,"repeats":1,"requiredWtypeId1":0,"requiredWtypeId2":0,"scope":1,"speed":-23,"stypeId":5,"successRate":100,"tpCost":0,"tpGain":0},
{"id":13,"animationId":43,"damage":{"critical":false,"elementId":0,"formula":"(20 * Math.Random(0,0.125)+1) * (2 + a.mat * (a.level + a.mat)/256)","type":3,"variance":0},"description":"Restores some HP to all targets. Has a very small chance to remove negative status effects.","effects":[],"hitType":0,"iconIndex":72,"message1":" casts %1!","message2":"","mpCost":26,"name":"Cura","note":"","occasion":0,"repeats":1,"requiredWtypeId1":0,"requiredWtypeId2":0,"scope":8,"speed":-23,"stypeId":5,"successRate":100,"tpCost":0,"tpGain":0},
{"id":14,"animationId":49,"damage":{"critical":false,"elementId":0,"formula":"b.mhp * 0.40","type":3,"variance":0},"description":"Revives one defeated target with 40% maximum HP.","effects":[{"code":22,"dataId":1,"value1":1,"value2":0}],"hitType":0,"iconIndex":72,"message1":" casts %1!","message2":"","mpCost":20,"name":"Raise","note":"","occasion":0,"repeats":1,"requiredWtypeId1":0,"requiredWtypeId2":0,"scope":9,"speed":-23,"stypeId":5,"successRate":100,"tpCost":0,"tpGain":0},
{"id":15,"animationId":54,"damage":{"critical":false,"elementId":0,"formula":"0","type":0,"variance":20},"description":"Removes beneficial status effects from one target. May remove Slow and Stop.","effects":[],"hitType":0,"iconIndex":72,"message1":" casts %1!","message2":"","mpCost":16,"name":"Dispel","note":"","occasion":1,"repeats":1,"requiredWtypeId1":0,"requiredWtypeId2":0,"scope":1,"speed":-23,"stypeId":5,"successRate":100,"tpCost":0,"tpGain":0},
{"id":16,"animationId":46,"damage":{"critical":false,"elementId":0,"formula":"0","type":0,"variance":20},"description":"Removes Stone or Petrify from one target.","effects":[],"hitType":0,"iconIndex":72,"message1":" casts %1!","message2":"","mpCost":12,"name":"Stona","note":"","occasion":0,"repeats":1,"requiredWtypeId1":0,"requiredWtypeId2":0,"scope":7,"speed":-23,"stypeId":5,"successRate":100,"tpCost":0,"tpGain":0},
{"id":17,"animationId":41,"damage":{"critical":false,"elementId":0,"formula":"(120 * Math.Random(0,0.125)+1) * (2 + a.mat * (a.level + a.mat)/256)","type":3,"variance":0},"description":"Restores a large amount of HP to one target.","effects":[],"hitType":0,"iconIndex":72,"message1":" casts %1!","message2":"","mpCost":24,"name":"Curaga","note":"","occasion":0,"repeats":1,"requiredWtypeId1":0,"requiredWtypeId2":0,"scope":7,"speed":-23,"stypeId":5,"successRate":100,"tpCost":0,"tpGain":0},
{"id":18,"animationId":52,"damage":{"critical":false,"elementId":0,"formula":"0","type":0,"variance":20},"description":"One target gains Regen, restoring some HP over time.","effects":[],"hitType":0,"iconIndex":72,"message1":" casts %1!","message2":"","mpCost":16,"name":"Regen","note":"","occasion":1,"repeats":1,"requiredWtypeId1":0,"requiredWtypeId2":0,"scope":7,"speed":-23,"stypeId":5,"successRate":100,"tpCost":0,"tpGain":0},
{"id":19,"animationId":46,"damage":{"critical":false,"elementId":0,"formula":"0","type":0,"variance":20},"description":"Removes Disease from one target.","effects":[],"hitType":0,"iconIndex":72,"message1":" casts %1!","message2":"","mpCost":20,"name":"Cleanse","note":"","occasion":0,"repeats":1,"requiredWtypeId1":0,"requiredWtypeId2":0,"scope":7,"speed":-23,"stypeId":5,"successRate":100,"tpCost":0,"tpGain":0},
{"id":20,"animationId":45,"damage":{"critical":false,"elementId":0,"formula":"0","type":0,"variance":20},"description":"Removes negative status effects from one target.","effects":[],"hitType":0,"iconIndex":72,"message1":" casts %1!","message2":"","mpCost":24,"name":"Esuna","note":"","occasion":0,"repeats":1,"requiredWtypeId1":0,"requiredWtypeId2":0,"scope":7,"speed":-23,"stypeId":5,"successRate":100,"tpCost":0,"tpGain":0},
{"id":21,"animationId":63,"damage":{"critical":false,"elementId":0,"formula":"0","type":0,"variance":20},"description":"Confuses one target.","effects":[],"hitType":2,"iconIndex":6,"message1":" casts %1!","message2":"","mpCost":10,"name":"Confuse","note":"","occasion":1,"repeats":1,"requiredWtypeId1":0,"requiredWtypeId2":0,"scope":1,"speed":-23,"stypeId":5,"successRate":70,"tpCost":0,"tpGain":0},
{"id":22,"animationId":51,"damage":{"critical":false,"elementId":0,"formula":"0","type":0,"variance":20},"description":"One target gains Faith, boosting Magick Attack.","effects":[{"code":31,"dataId":4,"value1":5,"value2":0}],"hitType":0,"iconIndex":73,"message1":" casts %1!","message2":"","mpCost":24,"name":"Faith","note":"","occasion":1,"repeats":1,"requiredWtypeId1":0,"requiredWtypeId2":0,"scope":7,"speed":-23,"stypeId":5,"successRate":100,"tpCost":0,"tpGain":0},
{"id":23,"animationId":51,"damage":{"critical":false,"elementId":0,"formula":"0","type":0,"variance":20},"description":"One target gains Bravery, boosting Attack.","effects":[{"code":31,"dataId":2,"value1":5,"value2":0}],"hitType":0,"iconIndex":73,"message1":" casts %1!","message2":"","mpCost":24,"name":"Bravery","note":"","occasion":1,"repeats":1,"requiredWtypeId1":0,"requiredWtypeId2":0,"scope":7,"speed":-23,"stypeId":5,"successRate":100,"tpCost":0,"tpGain":0},
{"id":24,"animationId":44,"damage":{"critical":false,"elementId":0,"formula":"(86 * Math.Random(0,0.125)+1) * (2 + a.mat * (a.level + a.mat)/256)","type":3,"variance":0},"description":"Restores a large amount of HP to all targets.","effects":[],"hitType":0,"iconIndex":72,"message1":" casts %1!","message2":"","mpCost":58,"name":"Curaja","note":"","occasion":0,"repeats":1,"requiredWtypeId1":0,"requiredWtypeId2":0,"scope":8,"speed":-23,"stypeId":5,"successRate":100,"tpCost":0,"tpGain":0},
{"id":25,"animationId":54,"damage":{"critical":false,"elementId":0,"formula":"0","type":0,"variance":20},"description":"Removes beneficial status effects from all targets. May remove Slow and Stop.","effects":[],"hitType":0,"iconIndex":72,"message1":" casts %1!","message2":"","mpCost":32,"name":"Dispelga","note":"","occasion":1,"repeats":1,"requiredWtypeId1":0,"requiredWtypeId2":0,"scope":2,"speed":-23,"stypeId":5,"successRate":100,"tpCost":0,"tpGain":0},
{"id":26,"animationId":50,"damage":{"critical":false,"elementId":0,"formula":"b.hp","type":3,"variance":0},"description":"Revives one defeated target with full HP.","effects":[{"code":22,"dataId":1,"value1":1,"value2":0}],"hitType":0,"iconIndex":72,"message1":" casts %1!","message2":"","mpCost":52,"name":"Arise","note":"","occasion":0,"repeats":1,"requiredWtypeId1":0,"requiredWtypeId2":0,"scope":9,"speed":-23,"stypeId":5,"successRate":100,"tpCost":0,"tpGain":0},
{"id":27,"animationId":99,"damage":{"critical":false,"elementId":10,"formula":"(157 * Math.random(0,0.125) +1) * (2 + a.mat * (a.level+a.mat)/256)","type":1,"variance":0},"description":"Deals heavy light-elemental damage to one target.","effects":[],"hitType":2,"iconIndex":70,"message1":" casts %1!","message2":"","mpCost":48,"name":"Holy","note":"","occasion":1,"repeats":1,"requiredWtypeId1":0,"requiredWtypeId2":0,"scope":1,"speed":-23,"stypeId":5,"successRate":100,"tpCost":0,"tpGain":0},
{"id":28,"animationId":47,"damage":{"critical":false,"elementId":0,"formula":"0","type":0,"variance":20},"description":"Removes negative status effects from all targets.","effects":[],"hitType":0,"iconIndex":72,"message1":" casts %1!","message2":"","mpCost":66,"name":"Esunaga","note":"","occasion":0,"repeats":1,"requiredWtypeId1":0,"requiredWtypeId2":0,"scope":8,"speed":-23,"stypeId":5,"successRate":100,"tpCost":0,"tpGain":0},
{"id":29,"animationId":53,"damage":{"critical":false,"elementId":0,"formula":"0","type":0,"variance":20},"description":"All targets gain Protect, boosting Defense.","effects":[{"code":31,"dataId":3,"value1":5,"value2":0}],"hitType":0,"iconIndex":73,"message1":" casts %1!","message2":"","mpCost":36,"name":"Protectga","note":"","occasion":1,"repeats":1,"requiredWtypeId1":0,"requiredWtypeId2":0,"scope":8,"speed":-23,"stypeId":5,"successRate":100,"tpCost":0,"tpGain":0},
{"id":30,"animationId":53,"damage":{"critical":false,"elementId":0,"formula":"0","type":0,"variance":20},"description":"All targets gain Shell, boosting Magick Defense.","effects":[{"code":31,"dataId":5,"value1":5,"value2":0}],"hitType":0,"iconIndex":73,"message1":" casts %1!","message2":"","mpCost":40,"name":"Shellga","note":"","occasion":1,"repeats":1,"requiredWtypeId1":0,"requiredWtypeId2":0,"scope":8,"speed":-23,"stypeId":5,"successRate":100,"tpCost":0,"tpGain":0},
{"id":31,"animationId":42,"damage":{"critical":false,"elementId":0,"formula":"b.mhp","type":3,"variance":0},"description":"Fully restores the HP of one target. Removes negative status effects.","effects":[],"hitType":0,"iconIndex":72,"message1":" casts %1!","message2":"","mpCost":72,"name":"Renew","note":"","occasion":0,"repeats":1,"requiredWtypeId1":0,"requiredWtypeId2":0,"scope":7,"speed":-23,"stypeId":5,"successRate":100,"tpCost":0,"tpGain":0},
{"id":32,"animationId":0,"damage":{"critical":false,"elementId":0,"formula":"0","type":0,"variance":20},"description":"","effects":[],"hitType":0,"iconIndex":0,"message1":"","message2":"","mpCost":0,"name":"","note":"","occasion":0,"repeats":1,"requiredWtypeId1":0,"requiredWtypeId2":0,"scope":1,"speed":0,"stypeId":1,"successRate":100,"tpCost":0,"tpGain":0},
{"id":33,"animationId":0,"damage":{"critical":false,"elementId":0,"formula":"0","type":0,"variance":20},"description":"","effects":[],"hitType":0,"iconIndex":0,"message1":"","message2":"","mpCost":0,"name":"--BLACK MAGICK--","note":"","occasion":0,"repeats":1,"requiredWtypeId1":0,"requiredWtypeId2":0,"scope":1,"speed":0,"stypeId":1,"successRate":100,"tpCost":0,"tpGain":0},
{"id":34,"animationId":66,"damage":{"critical":false,"elementId":4,"formula":"(67 * Math.random(0,0.125) +1) * (2 + a.mat * (a.level+a.mat)/256)","type":1,"variance":0},"description":"Deals fire-elemental magical damage to one target. May inflict the target with Oil.","effects":[],"hitType":2,"iconIndex":64,"message1":" casts %1!","message2":"","mpCost":6,"name":"Fire","note":"","occasion":1,"repeats":1,"requiredWtypeId1":0,"requiredWtypeId2":0,"scope":1,"speed":-23,"stypeId":2,"successRate":100,"tpCost":0,"tpGain":0},
{"id":35,"animationId":76,"damage":{"critical":false,"elementId":6,"formula":"(68 * Math.random(0,0.125) +1) * (2 + a.mat * (a.level+a.mat)/256)","type":1,"variance":0},"description":"Deals lightning-elemental magical damage to one target. May inflict the target with Disable.","effects":[],"hitType":2,"iconIndex":66,"message1":" casts %1!","message2":"","mpCost":8,"name":"Thunder","note":"","occasion":1,"repeats":1,"requiredWtypeId1":0,"requiredWtypeId2":0,"scope":1,"speed":-23,"stypeId":2,"successRate":100,"tpCost":0,"tpGain":0},
{"id":36,"animationId":76,"damage":{"critical":false,"elementId":6,"formula":"(68 * Math.random(0,0.125) +1) * (2 + a.mat * (a.level+a.mat)/256)","type":1,"variance":0},"description":"Deals ice-elemental magical damage to one target. May inflict the target with Disable.","effects":[],"hitType":2,"iconIndex":65,"message1":" casts %1!","message2":"","mpCost":8,"name":"Blizzard","note":"","occasion":1,"repeats":1,"requiredWtypeId1":0,"requiredWtypeId2":0,"scope":1,"speed":-23,"stypeId":2,"successRate":100,"tpCost":0,"tpGain":0},
{"id":37,"animationId":60,"damage":{"critical":false,"elementId":0,"formula":"0","type":0,"variance":20},"description":"Inflicts Blind on one target.","effects":[],"hitType":2,"iconIndex":3,"message1":" casts %1!","message2":"","mpCost":10,"name":"Blind","note":"","occasion":1,"repeats":1,"requiredWtypeId1":0,"requiredWtypeId2":0,"scope":1,"speed":-23,"stypeId":2,"successRate":75,"tpCost":0,"tpGain":0},
{"id":38,"animationId":81,"damage":{"critical":false,"elementId":7,"formula":"(37 * Math.random(0,0.125) +1) * (2 + a.mat * (a.level+a.mat)/256)","type":1,"variance":0},"description":"Deals water-elemental magical damage to one target. May inflict that target with Poison.","effects":[],"hitType":2,"iconIndex":67,"message1":" casts %1!","message2":"","mpCost":12,"name":"Water","note":"","occasion":1,"repeats":1,"requiredWtypeId1":0,"requiredWtypeId2":0,"scope":1,"speed":-23,"stypeId":2,"successRate":100,"tpCost":0,"tpGain":0},
{"id":39,"animationId":61,"damage":{"critical":false,"elementId":0,"formula":"0","type":0,"variance":20},"description":"Inflicts Silence on one target.","effects":[],"hitType":2,"iconIndex":4,"message1":" casts %1!","message2":"","mpCost":8,"name":"Silence","note":"","occasion":1,"repeats":1,"requiredWtypeId1":0,"requiredWtypeId2":0,"scope":1,"speed":-23,"stypeId":2,"successRate":75,"tpCost":0,"tpGain":0},
{"id":40,"animationId":91,"damage":{"critical":false,"elementId":9,"formula":"(51 * Math.random(0,0.125) +1) * (2 + a.mat * (a.level+a.mat)/256)","type":1,"variance":0},"description":"Deals wind-elemental magical damage to one target. May inflict that target with Silence.","effects":[],"hitType":2,"iconIndex":69,"message1":" casts %1!","message2":"","mpCost":14,"name":"Aero","note":"","occasion":1,"repeats":1,"requiredWtypeId1":0,"requiredWtypeId2":0,"scope":1,"speed":-23,"stypeId":2,"successRate":100,"tpCost":0,"tpGain":0},
{"id":41,"animationId":62,"damage":{"critical":false,"elementId":0,"formula":"0","type":0,"variance":20},"description":"Puts one target to sleep.","effects":[],"hitType":2,"iconIndex":8,"message1":" casts %1!","message2":"","mpCost":10,"name":"Sleep","note":"","occasion":1,"repeats":1,"requiredWtypeId1":0,"requiredWtypeId2":0,"scope":1,"speed":-23,"stypeId":2,"successRate":75,"tpCost":0,"tpGain":0},
{"id":42,"animationId":68,"damage":{"critical":false,"elementId":4,"formula":"(22 * Math.random(0,0.125) +1) * (2 + a.mat * (a.level+a.mat)/256)","type":1,"variance":0},"description":"Deals fire-elemental magical damage to all targets in range. May inflict those targets with Oil.","effects":[],"hitType":2,"iconIndex":64,"message1":" casts %1!","message2":"","mpCost":16,"name":"Fira","note":"","occasion":1,"repeats":1,"requiredWtypeId1":0,"requiredWtypeId2":0,"scope":2,"speed":-23,"stypeId":2,"successRate":100,"tpCost":0,"tpGain":0},
{"id":43,"animationId":59,"damage":{"critical":false,"elementId":0,"formula":"0","type":0,"variance":20},"description":"Poisons one target.","effects":[],"hitType":2,"iconIndex":2,"message1":"","message2":"","mpCost":8,"name":"Poison","note":"","occasion":1,"repeats":1,"requiredWtypeId1":0,"requiredWtypeId2":0,"scope":1,"speed":-23,"stypeId":2,"successRate":75,"tpCost":0,"tpGain":0},
{"id":44,"animationId":78,"damage":{"critical":false,"elementId":6,"formula":"(23 * Math.random(0,0.125) +1) * (2 + a.mat * (a.level+a.mat)/256)","type":1,"variance":0},"description":"Deals lightning-elemental magical damage to all targets in range. May inflict those targets with Disable.","effects":[],"hitType":2,"iconIndex":66,"message1":" casts %1!","message2":"","mpCost":18,"name":"Thundara","note":"","occasion":1,"repeats":1,"requiredWtypeId1":0,"requiredWtypeId2":0,"scope":2,"speed":-23,"stypeId":2,"successRate":100,"tpCost":0,"tpGain":0},
{"id":45,"animationId":73,"damage":{"critical":false,"elementId":5,"formula":"(25 * Math.random(0,0.125) +1) * (2 + a.mat * (a.level+a.mat)/256)","type":1,"variance":0},"description":"Deals ice-elemental magical damage to all targets in range. May inflict those targets with Disable.","effects":[],"hitType":2,"iconIndex":65,"message1":" casts %1!","message2":"","mpCost":20,"name":"Blizzara","note":"","occasion":1,"repeats":1,"requiredWtypeId1":0,"requiredWtypeId2":0,"scope":2,"speed":-23,"stypeId":2,"successRate":100,"tpCost":0,"tpGain":0},
{"id":46,"animationId":59,"damage":{"critical":false,"elementId":0,"formula":"(142 * Math.random(0,0.125) +1) * (2 + a.mat * (a.level+a.mat)/256)","type":1,"variance":0},"description":"Deals non-elemental magical damage to a target, and inflicts that target with Sap.","effects":[],"hitType":2,"iconIndex":78,"message1":" casts %1!","message2":"","mpCost":24,"name":"Bio","note":"","occasion":1,"repeats":1,"requiredWtypeId1":0,"requiredWtypeId2":0,"scope":1,"speed":-23,"stypeId":2,"successRate":100,"tpCost":0,"tpGain":0},
{"id":47,"animationId":60,"damage":{"critical":false,"elementId":0,"formula":"0","type":0,"variance":20},"description":"Inflicts Blind on all targets.","effects":[],"hitType":2,"iconIndex":3,"message1":" casts %1!","message2":"","mpCost":20,"name":"Blindga","note":"","occasion":1,"repeats":1,"requiredWtypeId1":0,"requiredWtypeId2":0,"scope":2,"speed":-23,"stypeId":2,"successRate":50,"tpCost":0,"tpGain":0},
{"id":48,"animationId":92,"damage":{"critical":false,"elementId":9,"formula":"(103 * Math.random(0,0.125) +1) * (2 + a.mat * (a.level+a.mat)/256)","type":1,"variance":0},"description":"Deals a large amount of wind-elemental magical damage to one target.","effects":[],"hitType":0,"iconIndex":69,"message1":" casts %1!","message2":"","mpCost":38,"name":"Aeroga","note":"","occasion":1,"repeats":1,"requiredWtypeId1":0,"requiredWtypeId2":0,"scope":1,"speed":-23,"stypeId":2,"successRate":100,"tpCost":0,"tpGain":0},
{"id":49,"animationId":61,"damage":{"critical":false,"elementId":0,"formula":"0","type":0,"variance":20},"description":"Inflicts Silence on all targets.","effects":[],"hitType":2,"iconIndex":4,"message1":" casts %1!","message2":"","mpCost":22,"name":"Silencega","note":"","occasion":1,"repeats":1,"requiredWtypeId1":0,"requiredWtypeId2":0,"scope":2,"speed":-23,"stypeId":2,"successRate":50,"tpCost":0,"tpGain":0},
{"id":50,"animationId":67,"damage":{"critical":false,"elementId":4,"formula":"(120 * Math.random(0,0.125) +1) * (2 + a.mat * (a.level+a.mat)/256)","type":1,"variance":0},"description":"Deals a large amount of fire-elemental magical damage to one target.","effects":[],"hitType":2,"iconIndex":64,"message1":" casts %1!","message2":"","mpCost":38,"name":"Firaga","note":"","occasion":1,"repeats":1,"requiredWtypeId1":0,"requiredWtypeId2":0,"scope":1,"speed":-23,"stypeId":2,"successRate":100,"tpCost":0,"tpGain":0},
{"id":51,"animationId":77,"damage":{"critical":false,"elementId":6,"formula":"(122 * Math.random(0,0.125) +1) * (2 + a.mat * (a.level+a.mat)/256)","type":1,"variance":0},"description":"Deals a large amount of lightning-elemental magical damage to one target.","effects":[],"hitType":2,"iconIndex":66,"message1":" casts %1!","message2":"","mpCost":40,"name":"Thundaga","note":"","occasion":1,"repeats":1,"requiredWtypeId1":0,"requiredWtypeId2":0,"scope":1,"speed":-23,"stypeId":2,"successRate":100,"tpCost":0,"tpGain":0},
{"id":52,"animationId":72,"damage":{"critical":false,"elementId":5,"formula":"(125 * Math.random(0,0.125) +1) * (2 + a.mat * (a.level+a.mat)/256)","type":1,"variance":0},"description":"Deals a large amount of ice-elemental magical damage to one target.","effects":[],"hitType":2,"iconIndex":65,"message1":" casts %1!","message2":"","mpCost":42,"name":"Blizzaga","note":"","occasion":1,"repeats":1,"requiredWtypeId1":0,"requiredWtypeId2":0,"scope":1,"speed":-23,"stypeId":2,"successRate":100,"tpCost":0,"tpGain":0},
{"id":53,"animationId":62,"damage":{"critical":false,"elementId":0,"formula":"0","type":0,"variance":20},"description":"Puts all targets to sleep.","effects":[],"hitType":2,"iconIndex":8,"message1":" casts %1!","message2":"","mpCost":26,"name":"Sleepga","note":"","occasion":1,"repeats":1,"requiredWtypeId1":0,"requiredWtypeId2":0,"scope":2,"speed":-23,"stypeId":2,"successRate":50,"tpCost":0,"tpGain":0},
{"id":54,"animationId":59,"damage":{"critical":false,"elementId":0,"formula":"0","type":0,"variance":20},"description":"Poisons all targets.","effects":[],"hitType":2,"iconIndex":2,"message1":" casts %1!","message2":"","mpCost":26,"name":"Toxify","note":"","occasion":1,"repeats":1,"requiredWtypeId1":0,"requiredWtypeId2":0,"scope":2,"speed":-23,"stypeId":2,"successRate":50,"tpCost":0,"tpGain":0},
{"id":55,"animationId":106,"damage":{"critical":false,"elementId":0,"formula":"(133 * Math.random(0,0.125) +1) * (2 + a.mat * (a.level+a.mat)/256)","type":1,"variance":0},"description":"Deals large non-elemental magical damage to all target.","effects":[],"hitType":2,"iconIndex":78,"message1":" casts %1!","message2":"","mpCost":34,"name":"Shock","note":"","occasion":1,"repeats":1,"requiredWtypeId1":0,"requiredWtypeId2":0,"scope":2,"speed":-23,"stypeId":2,"successRate":100,"tpCost":0,"tpGain":0},
{"id":56,"animationId":108,"damage":{"critical":false,"elementId":0,"formula":"(67 * Math.random(0,0.125) +1) * (2 + a.mat * (a.level+a.mat)/256)","type":1,"variance":0},"description":"Deals non-elemental magical damage to one target. May inflict those targets with Sap.","effects":[],"hitType":0,"iconIndex":78,"message1":" casts %1!","message2":"","mpCost":48,"name":"Bioga","note":"","occasion":1,"repeats":1,"requiredWtypeId1":0,"requiredWtypeId2":0,"scope":1,"speed":-23,"stypeId":2,"successRate":100,"tpCost":0,"tpGain":0},
{"id":57,"animationId":107,"damage":{"critical":false,"elementId":0,"formula":"(163 * Math.random(0,0.125) +1) * (2 + a.mat * (a.level+a.mat)/256)","type":1,"variance":0},"description":"Deals massive non-elemental magical damage to one target.","effects":[],"hitType":2,"iconIndex":78,"message1":" casts %1!","message2":"","mpCost":46,"name":"Flare","note":"","occasion":1,"repeats":1,"requiredWtypeId1":0,"requiredWtypeId2":0,"scope":1,"speed":-23,"stypeId":2,"successRate":100,"tpCost":0,"tpGain":0},
{"id":58,"animationId":109,"damage":{"critical":false,"elementId":0,"formula":"(190 * Math.random(0,0.125) +1) * (2 + a.mat * (a.level+a.mat)/256)","type":1,"variance":0},"description":"Deals massive non-elemental damage to all targets.","effects":[],"hitType":2,"iconIndex":78,"message1":" casts %1!","message2":"","mpCost":70,"name":"Scathe","note":"<Target: Everybody>","occasion":1,"repeats":1,"requiredWtypeId1":0,"requiredWtypeId2":0,"scope":0,"speed":-23,"stypeId":2,"successRate":100,"tpCost":0,"tpGain":0},
{"id":59,"animationId":0,"damage":{"critical":false,"elementId":0,"formula":"0","type":0,"variance":20},"description":"","effects":[],"hitType":0,"iconIndex":0,"message1":"","message2":"","mpCost":0,"name":"","note":"","occasion":0,"repeats":1,"requiredWtypeId1":0,"requiredWtypeId2":0,"scope":1,"speed":0,"stypeId":1,"successRate":100,"tpCost":0,"tpGain":0},
{"id":60,"animationId":0,"damage":{"critical":false,"elementId":0,"formula":"0","type":0,"variance":20},"description":"","effects":[],"hitType":0,"iconIndex":0,"message1":"","message2":"","mpCost":0,"name":"--TIME MAGICK--","note":"","occasion":0,"repeats":1,"requiredWtypeId1":0,"requiredWtypeId2":0,"scope":1,"speed":0,"stypeId":1,"successRate":100,"tpCost":0,"tpGain":0},
{"id":61,"animationId":55,"damage":{"critical":false,"elementId":0,"formula":"0","type":0,"variance":20},"description":"Slows one target, lowering Agility.","effects":[{"code":32,"dataId":6,"value1":5,"value2":0},{"code":32,"dataId":6,"value1":5,"value2":0}],"hitType":2,"iconIndex":74,"message1":" casts %1!","message2":"","mpCost":8,"name":"Slow","note":"","occasion":1,"repeats":1,"requiredWtypeId1":0,"requiredWtypeId2":0,"scope":1,"speed":-23,"stypeId":4,"successRate":65,"tpCost":0,"tpGain":0},
{"id":62,"animationId":64,"damage":{"critical":false,"elementId":0,"formula":"0","type":0,"variance":20},"description":"Pulls all enemies to one row, preventing them from moving.","effects":[],"hitType":2,"iconIndex":141,"message1":" casts %1!","message2":"","mpCost":14,"name":"Immobilize","note":"<After Eval>\nvar row = target.row();\nvar members = target.friendsUnit().aliveMembers();\nfor (var i = 0; i < members.length; ++i) {\n  var member = members[i];\n  if (member && member.row() !== row) {\n    member.setRow(row);\n  }\n}\n</After Eval>","occasion":1,"repeats":1,"requiredWtypeId1":0,"requiredWtypeId2":0,"scope":1,"speed":-23,"stypeId":4,"successRate":60,"tpCost":0,"tpGain":0},
{"id":63,"animationId":53,"damage":{"critical":false,"elementId":0,"formula":"0","type":0,"variance":20},"description":"One target gains Reflect.","effects":[],"hitType":0,"iconIndex":253,"message1":" casts %1!","message2":"","mpCost":12,"name":"Reflect","note":"","occasion":1,"repeats":1,"requiredWtypeId1":0,"requiredWtypeId2":0,"scope":7,"speed":-23,"stypeId":4,"successRate":100,"tpCost":0,"tpGain":0},
{"id":64,"animationId":64,"damage":{"critical":false,"elementId":0,"formula":"0","type":0,"variance":20},"description":"Inflicts Disable on all targets.","effects":[],"hitType":2,"iconIndex":9,"message1":" casts %1!","message2":"","mpCost":14,"name":"Disable","note":"","occasion":1,"repeats":1,"requiredWtypeId1":0,"requiredWtypeId2":0,"scope":2,"speed":-23,"stypeId":4,"successRate":50,"tpCost":0,"tpGain":0},
{"id":65,"animationId":40,"damage":{"critical":false,"elementId":0,"formula":"0","type":0,"variance":20},"description":"One target gains Invisible.","effects":[],"hitType":0,"iconIndex":82,"message1":" casts %1!","message2":"","mpCost":12,"name":"Vanish","note":"","occasion":1,"repeats":1,"requiredWtypeId1":0,"requiredWtypeId2":0,"scope":7,"speed":-23,"stypeId":4,"successRate":100,"tpCost":0,"tpGain":0},
{"id":66,"animationId":38,"damage":{"critical":false,"elementId":0,"formula":"(a.mhp - a.hp) * 2","type":1,"variance":0},"description":"Deals non-elemental magical damage to all targets based upon the difference between the caster's current and maximum HP.","effects":[],"hitType":2,"iconIndex":75,"message1":" casts %1!","message2":"","mpCost":18,"name":"Balance","note":"","occasion":1,"repeats":1,"requiredWtypeId1":0,"requiredWtypeId2":0,"scope":2,"speed":-23,"stypeId":4,"successRate":100,"tpCost":0,"tpGain":0},
{"id":67,"animationId":57,"damage":{"critical":false,"elementId":0,"formula":"b.mhp / 4","type":1,"variance":0},"description":"Deals 25% maximum HP damage to all targets.","effects":[],"hitType":2,"iconIndex":71,"message1":" casts %1!","message2":"","mpCost":12,"name":"Gravity","note":"","occasion":1,"repeats":1,"requiredWtypeId1":0,"requiredWtypeId2":0,"scope":2,"speed":-23,"stypeId":4,"successRate":70,"tpCost":0,"tpGain":0},
{"id":68,"animationId":52,"damage":{"critical":false,"elementId":0,"formula":"0","type":0,"variance":20},"description":"One target gains Haste, boosting Agility.","effects":[{"code":31,"dataId":6,"value1":5,"value2":0},{"code":31,"dataId":6,"value1":5,"value2":0}],"hitType":0,"iconIndex":73,"message1":" casts %1!","message2":"","mpCost":18,"name":"Haste","note":"","occasion":1,"repeats":1,"requiredWtypeId1":0,"requiredWtypeId2":0,"scope":7,"speed":-23,"stypeId":4,"successRate":100,"tpCost":0,"tpGain":0},
{"id":69,"animationId":64,"damage":{"critical":false,"elementId":0,"formula":"0","type":0,"variance":20},"description":"Stops one target, preventing it from acting.","effects":[],"hitType":2,"iconIndex":9,"message1":" casts %1!","message2":"","mpCost":20,"name":"Stop","note":"","occasion":1,"repeats":1,"requiredWtypeId1":0,"requiredWtypeId2":0,"scope":1,"speed":-23,"stypeId":4,"successRate":50,"tpCost":0,"tpGain":0},
{"id":70,"animationId":7,"damage":{"critical":false,"elementId":0,"formula":"0","type":0,"variance":20},"description":"Inflicts Sap on one target.","effects":[],"hitType":2,"iconIndex":14,"message1":" casts %1!","message2":"","mpCost":12,"name":"Bleed","note":"","occasion":1,"repeats":1,"requiredWtypeId1":0,"requiredWtypeId2":0,"scope":1,"speed":-23,"stypeId":4,"successRate":100,"tpCost":0,"tpGain":0},
{"id":71,"animationId":87,"damage":{"critical":false,"elementId":0,"formula":"0","type":0,"variance":20},"description":"Inflicts Petrify on one target.","effects":[],"hitType":2,"iconIndex":68,"message1":" casts %1!","message2":"","mpCost":14,"name":"Break","note":"","occasion":1,"repeats":1,"requiredWtypeId1":0,"requiredWtypeId2":0,"scope":1,"speed":-23,"stypeId":4,"successRate":65,"tpCost":0,"tpGain":0},
{"id":72,"animationId":65,"damage":{"critical":false,"elementId":0,"formula":"0","type":0,"variance":20},"description":"Inflicts Doom on one target.","effects":[],"hitType":2,"iconIndex":1,"message1":" casts %1!","message2":"","mpCost":8,"name":"Doom","note":"","occasion":1,"repeats":1,"requiredWtypeId1":0,"requiredWtypeId2":0,"scope":1,"speed":-23,"stypeId":4,"successRate":60,"tpCost":0,"tpGain":0},
{"id":73,"animationId":93,"damage":{"critical":false,"elementId":0,"formula":"0","type":0,"variance":20},"description":"All targets gain Float.","effects":[],"hitType":0,"iconIndex":297,"message1":" casts %1!","message2":"","mpCost":16,"name":"Float","note":"","occasion":1,"repeats":1,"requiredWtypeId1":0,"requiredWtypeId2":0,"scope":8,"speed":-23,"stypeId":4,"successRate":100,"tpCost":0,"tpGain":0},
{"id":74,"animationId":37,"damage":{"critical":false,"elementId":0,"formula":"0","type":0,"variance":20},"description":"Inflicts one target with Berserk.","effects":[],"hitType":2,"iconIndex":5,"message1":" casts %1!","message2":"","mpCost":10,"name":"Berserk","note":"","occasion":1,"repeats":1,"requiredWtypeId1":0,"requiredWtypeId2":0,"scope":7,"speed":-23,"stypeId":4,"successRate":70,"tpCost":0,"tpGain":0},
{"id":75,"animationId":40,"damage":{"critical":false,"elementId":0,"formula":"0","type":0,"variance":20},"description":"All targets gain Invisible.","effects":[],"hitType":0,"iconIndex":82,"message1":" casts %1!","message2":"","mpCost":24,"name":"Vanishga","note":"","occasion":1,"repeats":1,"requiredWtypeId1":0,"requiredWtypeId2":0,"scope":8,"speed":-23,"stypeId":4,"successRate":100,"tpCost":0,"tpGain":0},
{"id":76,"animationId":0,"damage":{"critical":false,"elementId":0,"formula":"0","type":0,"variance":20},"description":"Ends the battle.","effects":[{"code":44,"dataId":1,"value1":1,"value2":0}],"hitType":0,"iconIndex":82,"message1":" casts %1!","message2":"","mpCost":18,"name":"Warp","note":"<Target: Everybody>","occasion":1,"repeats":1,"requiredWtypeId1":0,"requiredWtypeId2":0,"scope":0,"speed":-23,"stypeId":4,"successRate":100,"tpCost":0,"tpGain":0},
{"id":77,"animationId":53,"damage":{"critical":false,"elementId":0,"formula":"0","type":0,"variance":20},"description":"All targets gain Reflect.","effects":[],"hitType":0,"iconIndex":253,"message1":" casts %1!","message2":"","mpCost":24,"name":"Reflectga","note":"","occasion":1,"repeats":1,"requiredWtypeId1":0,"requiredWtypeId2":0,"scope":8,"speed":-23,"stypeId":4,"successRate":100,"tpCost":0,"tpGain":0},
{"id":78,"animationId":55,"damage":{"critical":false,"elementId":0,"formula":"0","type":0,"variance":20},"description":"Slows all targets, lowering Agility.","effects":[{"code":32,"dataId":6,"value1":5,"value2":0},{"code":32,"dataId":6,"value1":5,"value2":0}],"hitType":2,"iconIndex":74,"message1":" casts %1!","message2":"","mpCost":24,"name":"Slowga","note":"","occasion":1,"repeats":1,"requiredWtypeId1":0,"requiredWtypeId2":0,"scope":2,"speed":-23,"stypeId":4,"successRate":60,"tpCost":0,"tpGain":0},
{"id":79,"animationId":57,"damage":{"critical":false,"elementId":0,"formula":"b.mhp / 2","type":1,"variance":0},"description":"Deals 50% maximum HP damage to all targets.","effects":[],"hitType":2,"iconIndex":71,"message1":" casts %1!","message2":"","mpCost":28,"name":"Graviga","note":"","occasion":1,"repeats":1,"requiredWtypeId1":0,"requiredWtypeId2":0,"scope":2,"speed":-23,"stypeId":4,"successRate":40,"tpCost":0,"tpGain":0},
{"id":80,"animationId":52,"damage":{"critical":false,"elementId":0,"formula":"0","type":0,"variance":20},"description":"All targets gain Haste, boosting Agility.","effects":[{"code":31,"dataId":6,"value1":5,"value2":0},{"code":31,"dataId":6,"value1":5,"value2":0}],"hitType":0,"iconIndex":73,"message1":" casts %1!","message2":"","mpCost":70,"name":"Hastega","note":"","occasion":1,"repeats":1,"requiredWtypeId1":0,"requiredWtypeId2":0,"scope":8,"speed":-23,"stypeId":4,"successRate":100,"tpCost":0,"tpGain":0},
{"id":81,"animationId":0,"damage":{"critical":false,"elementId":0,"formula":"0","type":0,"variance":20},"description":"","effects":[],"hitType":0,"iconIndex":0,"message1":"","message2":"","mpCost":0,"name":"","note":"","occasion":0,"repeats":1,"requiredWtypeId1":0,"requiredWtypeId2":0,"scope":1,"speed":0,"stypeId":1,"successRate":100,"tpCost":0,"tpGain":0},
{"id":82,"animationId":0,"damage":{"critical":false,"elementId":0,"formula":"0","type":0,"variance":20},"description":"","effects":[],"hitType":0,"iconIndex":0,"message1":"","message2":"","mpCost":0,"name":"--GREEN MAGICK--","note":"","occasion":0,"repeats":1,"requiredWtypeId1":0,"requiredWtypeId2":0,"scope":1,"speed":0,"stypeId":1,"successRate":100,"tpCost":0,"tpGain":0},
{"id":83,"animationId":37,"damage":{"critical":false,"elementId":0,"formula":"0","type":0,"variance":20},"description":"One target gains Decoy, drawing all physical attacks to them.","effects":[],"hitType":2,"iconIndex":77,"message1":" casts %1!","message2":"","mpCost":10,"name":"Decoy","note":"","occasion":1,"repeats":1,"requiredWtypeId1":0,"requiredWtypeId2":0,"scope":1,"speed":-23,"stypeId":3,"successRate":60,"tpCost":0,"tpGain":0},
{"id":84,"animationId":82,"damage":{"critical":false,"elementId":0,"formula":"0","type":0,"variance":20},"description":"Coats all targets in flammable oil.","effects":[],"hitType":2,"iconIndex":11,"message1":" casts %1!","message2":"","mpCost":8,"name":"Oil","note":"","occasion":1,"repeats":1,"requiredWtypeId1":0,"requiredWtypeId2":0,"scope":2,"speed":-23,"stypeId":3,"successRate":90,"tpCost":0,"tpGain":0},
{"id":85,"animationId":58,"damage":{"critical":false,"elementId":11,"formula":"(62 * Math.random(0,0.125) +1) * (2 + a.mat * (a.level+a.mat)/256)","type":5,"variance":0},"description":"Drains HP from one target.","effects":[],"hitType":2,"iconIndex":71,"message1":" casts %1!","message2":"","mpCost":18,"name":"Drain","note":"","occasion":1,"repeats":1,"requiredWtypeId1":0,"requiredWtypeId2":0,"scope":1,"speed":-23,"stypeId":3,"successRate":100,"tpCost":0,"tpGain":0},
{"id":86,"animationId":40,"damage":{"critical":false,"elementId":0,"formula":"0","type":0,"variance":20},"description":"Sets one target under Reverse, switching damage and healing done.","effects":[],"hitType":2,"iconIndex":75,"message1":" casts %1!","message2":"","mpCost":20,"name":"Reverse","note":"","occasion":1,"repeats":1,"requiredWtypeId1":0,"requiredWtypeId2":0,"scope":7,"speed":-23,"stypeId":3,"successRate":100,"tpCost":0,"tpGain":0},
{"id":87,"animationId":59,"damage":{"critical":false,"elementId":0,"formula":"0","type":0,"variance":20},"description":"Doubles maximum HP of one target.","effects":[{"code":31,"dataId":0,"value1":5,"value2":0},{"code":31,"dataId":0,"value1":5,"value2":0},{"code":31,"dataId":0,"value1":5,"value2":0},{"code":31,"dataId":0,"value1":5,"value2":0}],"hitType":0,"iconIndex":40,"message1":" casts %1!","message2":"","mpCost":32,"name":"Bubble","note":"","occasion":1,"repeats":1,"requiredWtypeId1":0,"requiredWtypeId2":0,"scope":7,"speed":23,"stypeId":3,"successRate":100,"tpCost":0,"tpGain":0},
{"id":88,"animationId":58,"damage":{"critical":false,"elementId":11,"formula":"(8 * Math.random(0,0.125) +1) * (2 + a.mat * (a.level+a.mat)/256)","type":6,"variance":0},"description":"Drains MP from one target.","effects":[],"hitType":2,"iconIndex":71,"message1":" casts %1!","message2":"","mpCost":2,"name":"Syphon","note":"","occasion":1,"repeats":1,"requiredWtypeId1":0,"requiredWtypeId2":0,"scope":1,"speed":-23,"stypeId":3,"successRate":60,"tpCost":0,"tpGain":0},
{"id":89,"animationId":0,"damage":{"critical":false,"elementId":0,"formula":"0","type":0,"variance":20},"description":"","effects":[],"hitType":0,"iconIndex":0,"message1":"","message2":"","mpCost":0,"name":"","note":"","occasion":0,"repeats":1,"requiredWtypeId1":0,"requiredWtypeId2":0,"scope":1,"speed":0,"stypeId":1,"successRate":100,"tpCost":0,"tpGain":0},
{"id":90,"animationId":0,"damage":{"critical":false,"elementId":0,"formula":"0","type":0,"variance":20},"description":"","effects":[],"hitType":0,"iconIndex":0,"message1":"","message2":"","mpCost":0,"name":"--ARCANE MAGICK--","note":"","occasion":0,"repeats":1,"requiredWtypeId1":0,"requiredWtypeId2":0,"scope":1,"speed":0,"stypeId":1,"successRate":100,"tpCost":0,"tpGain":0},
{"id":91,"animationId":101,"damage":{"critical":false,"elementId":11,"formula":"(91 * Math.random(0,0.125) +1) * (2 + a.mat * (a.level+a.mat)/256)","type":1,"variance":0},"description":"Deals darkness-elemental magical damage to one target. May inflict the target with Doom.","effects":[],"hitType":2,"iconIndex":71,"message1":" casts %1!","message2":"","mpCost":10,"name":"Dark","note":"","occasion":1,"repeats":1,"requiredWtypeId1":0,"requiredWtypeId2":0,"scope":1,"speed":-23,"stypeId":1,"successRate":100,"tpCost":0,"tpGain":0},
{"id":92,"animationId":103,"damage":{"critical":false,"elementId":11,"formula":"(46 * Math.random(0,0.125) +1) * (2 + a.mat * (a.level+a.mat)/256)","type":1,"variance":0},"description":"Deals darkness-elemental magical damage to all targets in range. May inflict those targets with Doom.","effects":[],"hitType":2,"iconIndex":71,"message1":" casts %1!","message2":"","mpCost":24,"name":"Darkra","note":"","occasion":1,"repeats":1,"requiredWtypeId1":0,"requiredWtypeId2":0,"scope":2,"speed":-23,"stypeId":1,"successRate":100,"tpCost":0,"tpGain":0},
{"id":93,"animationId":65,"damage":{"critical":false,"elementId":0,"formula":"0","type":0,"variance":20},"description":"Instantly defeats one target. Does not work on the undead.","effects":[{"code":21,"dataId":1,"value1":1,"value2":0}],"hitType":2,"iconIndex":1,"message1":" casts %1!","message2":"","mpCost":20,"name":"Death","note":"","occasion":1,"repeats":1,"requiredWtypeId1":0,"requiredWtypeId2":0,"scope":1,"speed":-23,"stypeId":1,"successRate":50,"tpCost":0,"tpGain":0},
{"id":94,"animationId":102,"damage":{"critical":false,"elementId":11,"formula":"(130 * Math.random(0,0.125) +1) * (2 + a.mat * (a.level+a.mat)/256)","type":1,"variance":0},"description":"Deals a large amount of darkness-elemental magical damage to one target.","effects":[],"hitType":2,"iconIndex":71,"message1":" casts %1!","message2":"","mpCost":38,"name":"Darkga","note":"","occasion":1,"repeats":1,"requiredWtypeId1":0,"requiredWtypeId2":0,"scope":1,"speed":-23,"stypeId":1,"successRate":100,"tpCost":0,"tpGain":0},
{"id":95,"animationId":69,"damage":{"critical":false,"elementId":4,"formula":"(173 * Math.random(0,0.125) +1) * (2 + a.mat * (a.level+a.mat)/256)","type":1,"variance":0},"description":"Deals massive fire-elemental magical damage to all targets.","effects":[],"hitType":2,"iconIndex":64,"message1":" casts %1!","message2":"","mpCost":60,"name":"Ardor","note":"<Multiple Elements: 9>","occasion":1,"repeats":1,"requiredWtypeId1":0,"requiredWtypeId2":0,"scope":2,"speed":-23,"stypeId":1,"successRate":100,"tpCost":0,"tpGain":0},
{"id":96,"animationId":0,"damage":{"critical":false,"elementId":0,"formula":"0","type":0,"variance":20},"description":"","effects":[],"hitType":0,"iconIndex":0,"message1":"","message2":"","mpCost":0,"name":"","note":"","occasion":0,"repeats":1,"requiredWtypeId1":0,"requiredWtypeId2":0,"scope":1,"speed":0,"stypeId":1,"successRate":100,"tpCost":0,"tpGain":0},
{"id":97,"animationId":0,"damage":{"critical":false,"elementId":0,"formula":"0","type":0,"variance":20},"description":"","effects":[],"hitType":0,"iconIndex":0,"message1":"","message2":"","mpCost":0,"name":"--TECHNICKS--","note":"","occasion":0,"repeats":1,"requiredWtypeId1":0,"requiredWtypeId2":0,"scope":1,"speed":0,"stypeId":1,"successRate":100,"tpCost":0,"tpGain":0},
{"id":98,"animationId":28,"damage":{"critical":false,"elementId":0,"formula":"0","type":0,"variance":20},"description":"Pilfers an item from an enemy.","effects":[],"hitType":1,"iconIndex":208,"message1":" uses %1!","message2":"","mpCost":0,"name":"Steal","note":"<Steal>","occasion":1,"repeats":1,"requiredWtypeId1":0,"requiredWtypeId2":0,"scope":1,"speed":-20,"stypeId":6,"successRate":100,"tpCost":20,"tpGain":0},
{"id":99,"animationId":34,"damage":{"critical":false,"elementId":0,"formula":"0","type":0,"variance":20},"description":"Reveals detailed information about an enemy.","effects":[],"hitType":0,"iconIndex":79,"message1":" uses %1!","message2":"","mpCost":0,"name":"Libra","note":"<Before Eval>\nif (target.isEnemy()) {\n  var id = target._enemyId;\n  $gameSystem.addHpGaugeEnemy(id);\n\n  var text = target.name() + '\\n';\n  text += '\\\\px[100]\\\\c[4]HP:\\\\c[0] ' + target.hp;\n  text += '/' + target.mhp;\n  text += '\\\\px[400]\\\\c[4]MP:\\\\c[0] ' + target.mp;\n  text += '/' + target.mmp;\n  text += '\\\\px[700]\\\\c[4]TP:\\\\c[0] ' + target.tp;\n  text += '\\n';\n  text += '\\\\px[100]\\\\c[4]ATK:\\\\c[0] ' + target.atk;\n  text += '\\\\px[400]\\\\c[4]MAT:\\\\c[0] ' + target.mat;\n  text += '\\\\px[700]\\\\c[4]AGI:\\\\c[0] ' + target.agi;\n  text += '\\n';\n  text += '\\\\px[100]\\\\c[4]DEF:\\\\c[0] ' + target.def;\n  text += '\\\\px[400]\\\\c[4]MDF:\\\\c[0] ' + target.mdf;\n  text += '\\\\px[700]\\\\c[4]LUK:\\\\c[0] ' + target.luk;\n  $gameMessage.add(text);\n \n  var weakness = '';\n  var resist = '';\n  var immune = '';\n  var absorb = '';\n  var elements = $dataSystem.elements;\n  for (var i = 1; i < elements.length; ++i) {\n    var name = elements[i];\n    var rate = target.elementRate(i);\n    if (rate > 1) {\n      weakness += name + ' ';\n    } else if (rate < 0) {\n      absorb += name + ' ';\n    } else if (rate === 0) {\n      immune += name + ' ';\n    } else if (rate < 1) {\n      resist += name + ' ';\n    }\n  }\n  if (weakness === '') weakness = 'None';\n  if (resist === '') resist = 'None';\n  if (immune === '') immune = 'None';\n  if (absorb === '') absorb = 'None';\n  weakness = '\\\\c[4]Weakness:\\\\c[0] ' + weakness + '\\n';\n  resist = '\\\\c[4]Resist:\\\\c[0] ' + resist + '\\n';\n  immune = '\\\\c[4]Immune:\\\\c[0] ' + immune + '\\n';\n  absorb = '\\\\c[4]Absorb:\\\\c[0] ' + absorb;\n  text = weakness + resist + immune + absorb;\n  $gameMessage.add(text);\n}\n</Before Eval>","occasion":1,"repeats":1,"requiredWtypeId1":0,"requiredWtypeId2":0,"scope":1,"speed":-10,"stypeId":6,"successRate":100,"tpCost":10,"tpGain":0},
{"id":100,"animationId":0,"damage":{"critical":false,"elementId":0,"formula":"0","type":0,"variance":20},"description":"","effects":[],"hitType":0,"iconIndex":0,"message1":"","message2":"","mpCost":0,"name":"First Aid","note":"","occasion":0,"repeats":1,"requiredWtypeId1":0,"requiredWtypeId2":0,"scope":1,"speed":0,"stypeId":1,"successRate":100,"tpCost":0,"tpGain":0},
{"id":101,"animationId":40,"damage":{"critical":false,"elementId":0,"formula":"Math.random(0,(a.level * 0.5)) + a.level","type":4,"variance":0},"description":"Restores some MP to the user.","effects":[],"hitType":0,"iconIndex":75,"message1":" uses %1!","message2":"","mpCost":0,"name":"Charge","note":"","occasion":1,"repeats":1,"requiredWtypeId1":0,"requiredWtypeId2":0,"scope":11,"speed":-40,"stypeId":6,"successRate":100,"tpCost":40,"tpGain":0},
{"id":102,"animationId":29,"damage":{"critical":false,"elementId":0,"formula":"0","type":1,"variance":0},"description":"Deals damage to all targets based upon time spent exploring.","effects":[],"hitType":1,"iconIndex":220,"message1":" uses %1!","message2":"","mpCost":0,"name":"Horology","note":"<Custom Damage Formula>\ninfo.playtime\n</Custom Damage Formula>","occasion":1,"repeats":1,"requiredWtypeId1":0,"requiredWtypeId2":0,"scope":2,"speed":-30,"stypeId":6,"successRate":90,"tpCost":30,"tpGain":0},
{"id":103,"animationId":0,"damage":{"critical":false,"elementId":0,"formula":"0","type":0,"variance":20},"description":"Captures a HP-critical target for additional loot.","effects":[],"hitType":1,"iconIndex":208,"message1":" uses %1!","message2":"","mpCost":0,"name":"Poach","note":"<After Eval>\nif (user.isActor() && target.isEnemy() && (target.isDead() || target.hp <= 0)) {\n  var id = target.enemyId();\n  var pool = [];\n  pool.push($dataItems[1]);\n  pool.push($dataItems[2]);\n  pool.push($dataItems[3]);\n  if (id === 1) {\n    pool.push($dataWeapons[1]);\n  } else if (id === 2) {\n    pool.push($dataWeapons[2]);\n    pool.push($dataWeapons[3]);\n  } else if (id === 3) {\n    pool.push($dataArmors[1]);\n    pool.push($dataArmors[2]);\n    pool.push($dataArmors[3]);\n  }\n  var item = pool[Math.floor(Math.random() * pool.length)];\n  if (item) {\n    target.startAnimation(2);\n    target.removeImmortal();\n    SoundManager.playShop();\n    $gameParty.gainItem(item, 1);\n    var msg = '<CENTER>' + user.name() + ' acquired \\\\i[' + item.iconIndex + ']' + item.name + ' from ' + target.name() + '!';\n    var wait = 60;\n    BattleManager.addText(msg, wait);\n  }\n}\n</After Eval>\n\n","occasion":1,"repeats":1,"requiredWtypeId1":0,"requiredWtypeId2":0,"scope":1,"speed":-30,"stypeId":6,"successRate":80,"tpCost":30,"tpGain":0},
{"id":104,"animationId":65,"damage":{"critical":true,"elementId":11,"formula":"a.weaponDamage(b) * 1.7","type":1,"variance":0},"description":"Consumes HP to deal damage to one enemy.","effects":[],"hitType":1,"iconIndex":10,"message1":" uses %1!","message2":"","mpCost":0,"name":"Souleater","note":"<HP Cost: 20%>\n<Bypass Armor Scaling>","occasion":1,"repeats":1,"requiredWtypeId1":0,"requiredWtypeId2":0,"scope":1,"speed":-30,"stypeId":6,"successRate":100,"tpCost":30,"tpGain":0},
{"id":105,"animationId":0,"damage":{"critical":false,"elementId":0,"formula":"0","type":0,"variance":20},"description":"","effects":[],"hitType":0,"iconIndex":0,"message1":"","message2":"","mpCost":0,"name":"Infuse","note":"","occasion":0,"repeats":1,"requiredWtypeId1":0,"requiredWtypeId2":0,"scope":1,"speed":0,"stypeId":1,"successRate":100,"tpCost":0,"tpGain":0},
{"id":106,"animationId":0,"damage":{"critical":false,"elementId":0,"formula":"0","type":0,"variance":20},"description":"","effects":[],"hitType":0,"iconIndex":0,"message1":"","message2":"","mpCost":0,"name":"1000 Needles","note":"","occasion":0,"repeats":1,"requiredWtypeId1":0,"requiredWtypeId2":0,"scope":1,"speed":0,"stypeId":1,"successRate":100,"tpCost":0,"tpGain":0},
{"id":107,"animationId":0,"damage":{"critical":false,"elementId":0,"formula":"0","type":0,"variance":20},"description":"","effects":[],"hitType":0,"iconIndex":0,"message1":"","message2":"","mpCost":0,"name":"Traveler","note":"","occasion":0,"repeats":1,"requiredWtypeId1":0,"requiredWtypeId2":0,"scope":1,"speed":0,"stypeId":1,"successRate":100,"tpCost":0,"tpGain":0},
{"id":108,"animationId":56,"damage":{"critical":false,"elementId":0,"formula":"0","type":0,"variance":20},"description":"Reduces one target's Magick Defense.","effects":[{"code":32,"dataId":5,"value1":5,"value2":0},{"code":32,"dataId":5,"value1":5,"value2":0}],"hitType":1,"iconIndex":53,"message1":" uses %1!","message2":"","mpCost":0,"name":"Shear","note":"","occasion":1,"repeats":1,"requiredWtypeId1":0,"requiredWtypeId2":0,"scope":1,"speed":-40,"stypeId":6,"successRate":70,"tpCost":40,"tpGain":0},
{"id":109,"animationId":63,"damage":{"critical":false,"elementId":0,"formula":"0","type":0,"variance":20},"description":"Confuses one target.","effects":[],"hitType":1,"iconIndex":6,"message1":" uses %1!","message2":"","mpCost":0,"name":"Charm","note":"","occasion":1,"repeats":1,"requiredWtypeId1":0,"requiredWtypeId2":0,"scope":1,"speed":-60,"stypeId":6,"successRate":90,"tpCost":60,"tpGain":0},
{"id":110,"animationId":55,"damage":{"critical":false,"elementId":0,"formula":"0","type":0,"variance":20},"description":"Reduces one target's Magick.","effects":[{"code":32,"dataId":4,"value1":5,"value2":0},{"code":32,"dataId":4,"value1":5,"value2":0}],"hitType":1,"iconIndex":52,"message1":" uses %1!","message2":"","mpCost":0,"name":"Addle","note":"","occasion":1,"repeats":1,"requiredWtypeId1":0,"requiredWtypeId2":0,"scope":1,"speed":-35,"stypeId":6,"successRate":45,"tpCost":35,"tpGain":0},
{"id":111,"animationId":0,"damage":{"critical":false,"elementId":0,"formula":"0","type":0,"variance":20},"description":"","effects":[],"hitType":0,"iconIndex":0,"message1":"","message2":"","mpCost":0,"name":"Expose","note":"","occasion":0,"repeats":1,"requiredWtypeId1":0,"requiredWtypeId2":0,"scope":1,"speed":0,"stypeId":1,"successRate":100,"tpCost":0,"tpGain":0},
{"id":112,"animationId":0,"damage":{"critical":false,"elementId":0,"formula":"0","type":0,"variance":20},"description":"","effects":[],"hitType":0,"iconIndex":0,"message1":"","message2":"","mpCost":0,"name":"Shades of Black","note":"","occasion":0,"repeats":1,"requiredWtypeId1":0,"requiredWtypeId2":0,"scope":1,"speed":0,"stypeId":1,"successRate":100,"tpCost":0,"tpGain":0},
{"id":113,"animationId":0,"damage":{"critical":false,"elementId":0,"formula":"0","type":0,"variance":20},"description":"","effects":[],"hitType":0,"iconIndex":0,"message1":"","message2":"","mpCost":0,"name":"Revive","note":"","occasion":0,"repeats":1,"requiredWtypeId1":0,"requiredWtypeId2":0,"scope":1,"speed":0,"stypeId":1,"successRate":100,"tpCost":0,"tpGain":0},
{"id":114,"animationId":0,"damage":{"critical":false,"elementId":0,"formula":"0","type":0,"variance":20},"description":"","effects":[],"hitType":0,"iconIndex":0,"message1":"","message2":"","mpCost":0,"name":"Gil Toss","note":"","occasion":0,"repeats":1,"requiredWtypeId1":0,"requiredWtypeId2":0,"scope":1,"speed":0,"stypeId":1,"successRate":100,"tpCost":0,"tpGain":0},
{"id":115,"animationId":106,"damage":{"critical":false,"elementId":0,"formula":"0","type":0,"variance":20},"description":"Deals a random amount of damage to random targets.","effects":[],"hitType":1,"iconIndex":78,"message1":" uses %1!","message2":"","mpCost":0,"name":"Numerology","note":"<Damage Formula>\n  Math.power(Math.RandomInt(64)+1,2)\n</Damage Formula>","occasion":1,"repeats":1,"requiredWtypeId1":0,"requiredWtypeId2":0,"scope":5,"speed":-20,"stypeId":6,"successRate":100,"tpCost":20,"tpGain":0},
{"id":116,"animationId":2,"damage":{"critical":false,"elementId":0,"formula":"0","type":0,"variance":20},"description":"Copies users status effects to target.","effects":[],"hitType":1,"iconIndex":75,"message1":" uses %1!","message2":"","mpCost":0,"name":"Stamp","note":"<Before Eval>\nvar states = user.states();\nfor (var i = 0; i < states.length; ++i) {\n  var state = states[i];\n  if state {\n  user.collectedState = state.id;\n  break;\n  }\n}\n  var stateId = user.collectedState;\n  target.addState(stateId);\n</Before Eval>","occasion":1,"repeats":1,"requiredWtypeId1":0,"requiredWtypeId2":0,"scope":1,"speed":-40,"stypeId":6,"successRate":80,"tpCost":40,"tpGain":0},
{"id":117,"animationId":0,"damage":{"critical":false,"elementId":0,"formula":"0","type":0,"variance":20},"description":"","effects":[],"hitType":0,"iconIndex":0,"message1":"","message2":"","mpCost":0,"name":"Sight Unseeing","note":"","occasion":0,"repeats":1,"requiredWtypeId1":0,"requiredWtypeId2":0,"scope":1,"speed":0,"stypeId":1,"successRate":100,"tpCost":0,"tpGain":0},
{"id":118,"animationId":55,"damage":{"critical":false,"elementId":0,"formula":"0","type":0,"variance":20},"description":"Adds one elemental weakness to one enemy.","effects":[],"hitType":1,"iconIndex":74,"message1":" uses %1!","message2":"","mpCost":0,"name":"Achilles","note":"<Custom Establish Effect>\n{\n  var actionElements = this.getItemElements();\n  var matchingElements = [4, 5, 6, 7, 8, 9, 10, 11];\n  var condition = false;\n  for (var i = 0; i < actionElements.length; ++i) {\n    if (matchingElements.contains(actionElements[i])) {\n      condition = true;\n      break;\n    }\n  }\n  if (condition) {\n    var exposedState = 82;\n    target.addState(exposedState);\n  }\n}\n</Custom Establish Effect>","occasion":1,"repeats":1,"requiredWtypeId1":0,"requiredWtypeId2":0,"scope":1,"speed":-40,"stypeId":6,"successRate":50,"tpCost":40,"tpGain":0},
{"id":119,"animationId":0,"damage":{"critical":false,"elementId":0,"formula":"0","type":0,"variance":20},"description":"","effects":[],"hitType":0,"iconIndex":0,"message1":"","message2":"","mpCost":0,"name":"Wither","note":"","occasion":0,"repeats":1,"requiredWtypeId1":0,"requiredWtypeId2":0,"scope":1,"speed":0,"stypeId":1,"successRate":100,"tpCost":0,"tpGain":0},
{"id":120,"animationId":0,"damage":{"critical":false,"elementId":0,"formula":"0","type":0,"variance":20},"description":"","effects":[],"hitType":0,"iconIndex":0,"message1":"","message2":"","mpCost":0,"name":"Bonecrusher","note":"","occasion":0,"repeats":1,"requiredWtypeId1":0,"requiredWtypeId2":0,"scope":1,"speed":0,"stypeId":1,"successRate":100,"tpCost":0,"tpGain":0},
{"id":121,"animationId":0,"damage":{"critical":false,"elementId":-1,"formula":"Math.random(0,(a.atk * b.level) -1)","type":1,"variance":0},"description":"Deal ranged damage with a melee weapon.","effects":[],"hitType":0,"iconIndex":76,"message1":" uses %1!","message2":"","mpCost":0,"name":"Telekenesis","note":"","occasion":0,"repeats":1,"requiredWtypeId1":0,"requiredWtypeId2":0,"scope":1,"speed":-30,"stypeId":6,"successRate":80,"tpCost":30,"tpGain":0},
{"id":122,"animationId":0,"damage":{"critical":false,"elementId":0,"formula":"0","type":0,"variance":20},"description":"","effects":[],"hitType":0,"iconIndex":0,"message1":"","message2":"","mpCost":0,"name":"","note":"","occasion":0,"repeats":1,"requiredWtypeId1":0,"requiredWtypeId2":0,"scope":1,"speed":0,"stypeId":1,"successRate":100,"tpCost":0,"tpGain":0},
{"id":123,"animationId":0,"damage":{"critical":false,"elementId":0,"formula":"0","type":0,"variance":20},"description":"","effects":[],"hitType":0,"iconIndex":0,"message1":"","message2":"","mpCost":0,"name":"","note":"","occasion":0,"repeats":1,"requiredWtypeId1":0,"requiredWtypeId2":0,"scope":1,"speed":0,"stypeId":1,"successRate":100,"tpCost":0,"tpGain":0},
{"id":124,"animationId":0,"damage":{"critical":false,"elementId":0,"formula":"0","type":0,"variance":20},"description":"","effects":[],"hitType":0,"iconIndex":0,"message1":"","message2":"","mpCost":0,"name":"","note":"","occasion":0,"repeats":1,"requiredWtypeId1":0,"requiredWtypeId2":0,"scope":1,"speed":0,"stypeId":1,"successRate":100,"tpCost":0,"tpGain":0},
{"id":125,"animationId":0,"damage":{"critical":false,"elementId":0,"formula":"0","type":0,"variance":20},"description":"","effects":[],"hitType":0,"iconIndex":0,"message1":"","message2":"","mpCost":0,"name":"","note":"","occasion":0,"repeats":1,"requiredWtypeId1":0,"requiredWtypeId2":0,"scope":1,"speed":0,"stypeId":1,"successRate":100,"tpCost":0,"tpGain":0},
{"id":126,"animationId":0,"damage":{"critical":false,"elementId":0,"formula":"0","type":0,"variance":20},"description":"","effects":[],"hitType":0,"iconIndex":0,"message1":"","message2":"","mpCost":0,"name":"","note":"","occasion":0,"repeats":1,"requiredWtypeId1":0,"requiredWtypeId2":0,"scope":1,"speed":0,"stypeId":1,"successRate":100,"tpCost":0,"tpGain":0},
{"id":127,"animationId":0,"damage":{"critical":false,"elementId":0,"formula":"0","type":0,"variance":20},"description":"","effects":[],"hitType":0,"iconIndex":0,"message1":"","message2":"","mpCost":0,"name":"","note":"","occasion":0,"repeats":1,"requiredWtypeId1":0,"requiredWtypeId2":0,"scope":1,"speed":0,"stypeId":1,"successRate":100,"tpCost":0,"tpGain":0},
{"id":128,"animationId":0,"damage":{"critical":false,"elementId":0,"formula":"0","type":0,"variance":20},"description":"","effects":[],"hitType":0,"iconIndex":0,"message1":"","message2":"","mpCost":0,"name":"","note":"","occasion":0,"repeats":1,"requiredWtypeId1":0,"requiredWtypeId2":0,"scope":1,"speed":0,"stypeId":1,"successRate":100,"tpCost":0,"tpGain":0},
{"id":129,"animationId":0,"damage":{"critical":false,"elementId":0,"formula":"0","type":0,"variance":20},"description":"","effects":[],"hitType":0,"iconIndex":0,"message1":"","message2":"","mpCost":0,"name":"","note":"","occasion":0,"repeats":1,"requiredWtypeId1":0,"requiredWtypeId2":0,"scope":1,"speed":0,"stypeId":1,"successRate":100,"tpCost":0,"tpGain":0},
{"id":130,"animationId":0,"damage":{"critical":false,"elementId":0,"formula":"0","type":0,"variance":20},"description":"","effects":[],"hitType":0,"iconIndex":0,"message1":"","message2":"","mpCost":0,"name":"","note":"","occasion":0,"repeats":1,"requiredWtypeId1":0,"requiredWtypeId2":0,"scope":1,"speed":0,"stypeId":1,"successRate":100,"tpCost":0,"tpGain":0}
]